{"TIME":{"0":"01-Jan","1":"02-Jan","2":"03-Jan","3":"04-Jan","4":"05-Jan","5":"06-Jan","6":"07-Jan","7":"08-Jan","8":"09-Jan","9":"10-Jan","10":"11-Jan","11":"12-Jan","12":"13-Jan","13":"14-Jan","14":"15-Jan","15":"16-Jan","16":"17-Jan","17":"18-Jan","18":"19-Jan","19":"20-Jan","20":"21-Jan","21":"22-Jan","22":"23-Jan","23":"24-Jan","24":"25-Jan","25":"26-Jan","26":"27-Jan","27":"28-Jan","28":"29-Jan","29":"30-Jan","30":"31-Jan","31":"01-Feb","32":"02-Feb","33":"03-Feb","34":"04-Feb","35":"05-Feb","36":"06-Feb","37":"07-Feb","38":"08-Feb","39":"09-Feb","40":"10-Feb","41":"11-Feb","42":"12-Feb","43":"13-Feb","44":"14-Feb","45":"15-Feb","46":"16-Feb","47":"17-Feb","48":"18-Feb","49":"19-Feb","50":"20-Feb","51":"21-Feb","52":"22-Feb","53":"23-Feb","54":"24-Feb","55":"25-Feb","56":"26-Feb","57":"27-Feb","58":"28-Feb","59":"29-Feb","60":"01-Mar","61":"02-Mar","62":"03-Mar","63":"04-Mar","64":"05-Mar","65":"06-Mar","66":"07-Mar","67":"08-Mar","68":"09-Mar","69":"10-Mar","70":"11-Mar","71":"12-Mar","72":"13-Mar","73":"14-Mar","74":"15-Mar","75":"16-Mar","76":"17-Mar","77":"18-Mar","78":"19-Mar","79":"20-Mar","80":"21-Mar","81":"22-Mar","82":"23-Mar","83":"24-Mar","84":"25-Mar","85":"26-Mar","86":"27-Mar","87":"28-Mar","88":"29-Mar","89":"30-Mar","90":"31-Mar","91":"01-Apr","92":"02-Apr","93":"03-Apr","94":"04-Apr","95":"05-Apr","96":"06-Apr","97":"07-Apr","98":"08-Apr","99":"09-Apr","100":"10-Apr","101":"11-Apr","102":"12-Apr","103":"13-Apr","104":"14-Apr","105":"15-Apr","106":"16-Apr","107":"17-Apr","108":"18-Apr","109":"19-Apr","110":"20-Apr","111":"21-Apr","112":"22-Apr","113":"23-Apr","114":"24-Apr","115":"25-Apr","116":"26-Apr","117":"27-Apr","118":"28-Apr","119":"29-Apr","120":"30-Apr","121":"01-May","122":"02-May","123":"03-May","124":"04-May","125":"05-May","126":"06-May","127":"07-May","128":"08-May","129":"09-May","130":"10-May","131":"11-May","132":"12-May","133":"13-May","134":"14-May","135":"15-May","136":"16-May","137":"17-May","138":"18-May","139":"19-May","140":"20-May","141":"21-May","142":"22-May","143":"23-May","144":"24-May","145":"25-May","146":"26-May","147":"27-May","148":"28-May","149":"29-May","150":"30-May","151":"31-May","152":"01-Jun","153":"02-Jun","154":"03-Jun","155":"04-Jun","156":"05-Jun","157":"06-Jun","158":"07-Jun","159":"08-Jun","160":"09-Jun","161":"10-Jun","162":"11-Jun","163":"12-Jun","164":"13-Jun","165":"14-Jun","166":"15-Jun","167":"16-Jun","168":"17-Jun","169":"18-Jun","170":"19-Jun","171":"20-Jun","172":"21-Jun","173":"22-Jun","174":"23-Jun","175":"24-Jun","176":"25-Jun","177":"26-Jun","178":"27-Jun","179":"28-Jun","180":"29-Jun","181":"30-Jun","182":"01-Jul","183":"02-Jul","184":"03-Jul","185":"04-Jul","186":"05-Jul","187":"06-Jul","188":"07-Jul","189":"08-Jul","190":"09-Jul","191":"10-Jul","192":"11-Jul","193":"12-Jul","194":"13-Jul","195":"14-Jul","196":"15-Jul","197":"16-Jul","198":"17-Jul","199":"18-Jul","200":"19-Jul","201":"20-Jul","202":"21-Jul","203":"22-Jul","204":"23-Jul","205":"24-Jul","206":"25-Jul","207":"26-Jul","208":"27-Jul","209":"28-Jul","210":"29-Jul","211":"30-Jul","212":"31-Jul","213":"01-Aug","214":"02-Aug","215":"03-Aug","216":"04-Aug","217":"05-Aug","218":"06-Aug","219":"07-Aug","220":"08-Aug","221":"09-Aug","222":"10-Aug","223":"11-Aug","224":"12-Aug","225":"13-Aug","226":"14-Aug","227":"15-Aug","228":"16-Aug","229":"17-Aug","230":"18-Aug","231":"19-Aug","232":"20-Aug","233":"21-Aug","234":"22-Aug","235":"23-Aug","236":"24-Aug","237":"25-Aug","238":"26-Aug","239":"27-Aug","240":"28-Aug","241":"29-Aug","242":"30-Aug","243":"31-Aug","244":"01-Sep","245":"02-Sep","246":"03-Sep","247":"04-Sep","248":"05-Sep","249":"06-Sep","250":"07-Sep","251":"08-Sep","252":"09-Sep","253":"10-Sep","254":"11-Sep","255":"12-Sep","256":"13-Sep","257":"14-Sep","258":"15-Sep","259":"16-Sep","260":"17-Sep","261":"18-Sep","262":"19-Sep","263":"20-Sep","264":"21-Sep","265":"22-Sep","266":"23-Sep","267":"24-Sep","268":"25-Sep","269":"26-Sep","270":"27-Sep","271":"28-Sep","272":"29-Sep","273":"30-Sep","274":"01-Oct","275":"02-Oct","276":"03-Oct","277":"04-Oct","278":"05-Oct","279":"06-Oct","280":"07-Oct","281":"08-Oct","282":"09-Oct","283":"10-Oct","284":"11-Oct","285":"12-Oct","286":"13-Oct","287":"14-Oct","288":"15-Oct","289":"16-Oct","290":"17-Oct","291":"18-Oct","292":"19-Oct","293":"20-Oct","294":"21-Oct","295":"22-Oct","296":"23-Oct","297":"24-Oct","298":"25-Oct","299":"26-Oct","300":"27-Oct","301":"28-Oct","302":"29-Oct","303":"30-Oct","304":"31-Oct","305":"01-Nov","306":"02-Nov","307":"03-Nov","308":"04-Nov","309":"05-Nov","310":"06-Nov","311":"07-Nov","312":"08-Nov","313":"09-Nov","314":"10-Nov","315":"11-Nov","316":"12-Nov","317":"13-Nov","318":"14-Nov","319":"15-Nov","320":"16-Nov","321":"17-Nov","322":"18-Nov","323":"19-Nov","324":"20-Nov","325":"21-Nov","326":"22-Nov","327":"23-Nov","328":"24-Nov","329":"25-Nov","330":"26-Nov","331":"27-Nov","332":"28-Nov","333":"29-Nov","334":"30-Nov","335":"01-Dec","336":"02-Dec","337":"03-Dec","338":"04-Dec","339":"05-Dec","340":"06-Dec","341":"07-Dec","342":"08-Dec","343":"09-Dec","344":"10-Dec","345":"11-Dec","346":"12-Dec","347":"13-Dec","348":"14-Dec","349":"15-Dec","350":"16-Dec","351":"17-Dec","352":"18-Dec","353":"19-Dec","354":"20-Dec","355":"21-Dec","356":"22-Dec","357":"23-Dec","358":"24-Dec","359":"25-Dec","360":"26-Dec","361":"27-Dec","362":"28-Dec","363":"29-Dec","364":"30-Dec","365":"31-Dec"},"RAINFALL":{"0":0.18,"1":0.32,"2":0.7,"3":0.2,"4":0.05,"5":0.08,"6":0.69,"7":0.27,"8":1.02,"9":0.48,"10":0.51,"11":0.78,"12":0.01,"13":0.38,"14":0.32,"15":0.79,"16":0.02,"17":0.02,"18":0.06,"19":0.14,"20":0.59,"21":0.64,"22":0.27,"23":0.15,"24":0.15,"25":0.77,"26":0.55,"27":0.25,"28":0.28,"29":0.9,"30":0.14,"31":0.76,"32":0.24,"33":0.51,"34":0.36,"35":0.49,"36":0.89,"37":0.84,"38":0.88,"39":0.82,"40":0.21,"41":0.2,"42":0.93,"43":0.77,"44":0.54,"45":0.49,"46":0.95,"47":0.53,"48":0.25,"49":0.43,"50":0.35,"51":0.36,"52":0.09,"53":0.09,"54":0.59,"55":0.96,"56":0.39,"57":0.64,"58":0.29,"59":1.27,"60":0.51,"61":0.69,"62":0.43,"63":1.25,"64":0.61,"65":0.36,"66":0.64,"67":0.3,"68":0.45,"69":0.37,"70":0.9,"71":0.86,"72":0.18,"73":0.27,"74":0.31,"75":0.18,"76":0.38,"77":0.79,"78":0.34,"79":0.53,"80":0.44,"81":0.78,"82":1.07,"83":0.12,"84":0.32,"85":0.74,"86":0.45,"87":0.36,"88":0.51,"89":1.13,"90":1.0,"91":0.43,"92":0.37,"93":0.64,"94":0.3,"95":0.5,"96":0.49,"97":0.46,"98":0.55,"99":0.64,"100":0.42,"101":0.05,"102":0.24,"103":0.12,"104":0.26,"105":0.46,"106":0.51,"107":0.56,"108":0.54,"109":0.81,"110":0.55,"111":0.38,"112":0.5,"113":0.39,"114":0.41,"115":1.34,"116":0.59,"117":0.65,"118":0.3,"119":0.8,"120":1.36,"121":1.16,"122":0.59,"123":0.63,"124":0.62,"125":0.65,"126":1.06,"127":0.56,"128":0.36,"129":0.43,"130":0.4,"131":0.87,"132":0.8,"133":0.81,"134":1.14,"135":1.43,"136":1.26,"137":0.52,"138":1.05,"139":0.55,"140":0.7,"141":0.83,"142":0.78,"143":0.85,"144":0.86,"145":0.46,"146":0.5,"147":1.98,"148":1.36,"149":1.83,"150":1.37,"151":1.34,"152":1.55,"153":1.56,"154":2.3,"155":2.46,"156":2.27,"157":2.77,"158":2.17,"159":1.75,"160":4.06,"161":6.2,"162":5.51,"163":4.12,"164":4.94,"165":6.84,"166":8.53,"167":7.14,"168":7.39,"169":6.48,"170":7.27,"171":9.71,"172":11.62,"173":12.52,"174":11.17,"175":11.1,"176":10.49,"177":10.34,"178":9.65,"179":10.72,"180":8.72,"181":12.45,"182":9.54,"183":11.88,"184":10.56,"185":11.35,"186":15.81,"187":13.0,"188":12.88,"189":12.95,"190":15.66,"191":11.04,"192":9.88,"193":10.33,"194":13.37,"195":10.37,"196":12.16,"197":16.4,"198":15.76,"199":11.2,"200":12.4,"201":12.42,"202":16.22,"203":20.04,"204":10.42,"205":10.98,"206":8.01,"207":10.21,"208":14.59,"209":15.21,"210":13.64,"211":15.18,"212":16.21,"213":7.75,"214":16.11,"215":14.73,"216":17.18,"217":15.81,"218":11.13,"219":12.57,"220":17.72,"221":12.43,"222":12.21,"223":13.83,"224":14.8,"225":16.18,"226":14.99,"227":14.88,"228":17.71,"229":12.81,"230":11.13,"231":15.31,"232":18.78,"233":12.18,"234":13.56,"235":11.1,"236":9.48,"237":8.85,"238":8.62,"239":12.55,"240":11.84,"241":12.24,"242":10.02,"243":8.97,"244":8.34,"245":11.03,"246":10.71,"247":14.86,"248":9.9,"249":12.21,"250":11.76,"251":11.06,"252":10.77,"253":9.48,"254":11.52,"255":10.29,"256":9.25,"257":11.29,"258":5.71,"259":5.5,"260":6.01,"261":7.52,"262":6.13,"263":4.4,"264":6.63,"265":6.1,"266":7.02,"267":6.82,"268":4.53,"269":4.05,"270":3.82,"271":2.29,"272":2.94,"273":4.59,"274":3.21,"275":4.2,"276":3.1,"277":3.53,"278":2.59,"279":2.34,"280":2.23,"281":3.19,"282":3.0,"283":1.25,"284":0.97,"285":2.06,"286":2.41,"287":1.3,"288":1.11,"289":1.72,"290":1.48,"291":1.72,"292":1.32,"293":1.6,"294":1.41,"295":1.0,"296":1.47,"297":1.58,"298":1.81,"299":0.72,"300":0.42,"301":0.36,"302":0.67,"303":1.27,"304":0.1,"305":0.39,"306":0.41,"307":0.95,"308":0.3,"309":0.37,"310":0.4,"311":0.43,"312":0.07,"313":0.68,"314":1.01,"315":0.06,"316":0.1,"317":0.03,"318":0.07,"319":0.1,"320":0.1,"321":0.33,"322":0.15,"323":0.43,"324":0.29,"325":0.1,"326":0.22,"327":0.16,"328":0.11,"329":0.19,"330":0.16,"331":0.18,"332":0.07,"333":0.11,"334":0.18,"335":0.39,"336":0.4,"337":0.05,"338":0.3,"339":0.07,"340":0.06,"341":0.73,"342":0.21,"343":0.28,"344":0.19,"345":0.1,"346":0.12,"347":0.11,"348":0.67,"349":0.06,"350":0.05,"351":0.32,"352":1.08,"353":0.04,"354":0.0,"355":0.01,"356":0.4,"357":0.21,"358":0.08,"359":0.42,"360":0.11,"361":0.07,"362":0.21,"363":0.39,"364":0.59,"365":0.18}}