{"TIME":{"0":"01-Jan","1":"02-Jan","2":"03-Jan","3":"04-Jan","4":"05-Jan","5":"06-Jan","6":"07-Jan","7":"08-Jan","8":"09-Jan","9":"10-Jan","10":"11-Jan","11":"12-Jan","12":"13-Jan","13":"14-Jan","14":"15-Jan","15":"16-Jan","16":"17-Jan","17":"18-Jan","18":"19-Jan","19":"20-Jan","20":"21-Jan","21":"22-Jan","22":"23-Jan","23":"24-Jan","24":"25-Jan","25":"26-Jan","26":"27-Jan","27":"28-Jan","28":"29-Jan","29":"30-Jan","30":"31-Jan","31":"01-Feb","32":"02-Feb","33":"03-Feb","34":"04-Feb","35":"05-Feb","36":"06-Feb","37":"07-Feb","38":"08-Feb","39":"09-Feb","40":"10-Feb","41":"11-Feb","42":"12-Feb","43":"13-Feb","44":"14-Feb","45":"15-Feb","46":"16-Feb","47":"17-Feb","48":"18-Feb","49":"19-Feb","50":"20-Feb","51":"21-Feb","52":"22-Feb","53":"23-Feb","54":"24-Feb","55":"25-Feb","56":"26-Feb","57":"27-Feb","58":"28-Feb","59":"29-Feb","60":"01-Mar","61":"02-Mar","62":"03-Mar","63":"04-Mar","64":"05-Mar","65":"06-Mar","66":"07-Mar","67":"08-Mar","68":"09-Mar","69":"10-Mar","70":"11-Mar","71":"12-Mar","72":"13-Mar","73":"14-Mar","74":"15-Mar","75":"16-Mar","76":"17-Mar","77":"18-Mar","78":"19-Mar","79":"20-Mar","80":"21-Mar","81":"22-Mar","82":"23-Mar","83":"24-Mar","84":"25-Mar","85":"26-Mar","86":"27-Mar","87":"28-Mar","88":"29-Mar","89":"30-Mar","90":"31-Mar","91":"01-Apr","92":"02-Apr","93":"03-Apr","94":"04-Apr","95":"05-Apr","96":"06-Apr","97":"07-Apr","98":"08-Apr","99":"09-Apr","100":"10-Apr","101":"11-Apr","102":"12-Apr","103":"13-Apr","104":"14-Apr","105":"15-Apr","106":"16-Apr","107":"17-Apr","108":"18-Apr","109":"19-Apr","110":"20-Apr","111":"21-Apr","112":"22-Apr","113":"23-Apr","114":"24-Apr","115":"25-Apr","116":"26-Apr","117":"27-Apr","118":"28-Apr","119":"29-Apr","120":"30-Apr","121":"01-May","122":"02-May","123":"03-May","124":"04-May","125":"05-May","126":"06-May","127":"07-May","128":"08-May","129":"09-May","130":"10-May","131":"11-May","132":"12-May","133":"13-May","134":"14-May","135":"15-May","136":"16-May","137":"17-May","138":"18-May","139":"19-May","140":"20-May","141":"21-May","142":"22-May","143":"23-May","144":"24-May","145":"25-May","146":"26-May","147":"27-May","148":"28-May","149":"29-May","150":"30-May","151":"31-May","152":"01-Jun","153":"02-Jun","154":"03-Jun","155":"04-Jun","156":"05-Jun","157":"06-Jun","158":"07-Jun","159":"08-Jun","160":"09-Jun","161":"10-Jun","162":"11-Jun","163":"12-Jun","164":"13-Jun","165":"14-Jun","166":"15-Jun","167":"16-Jun","168":"17-Jun","169":"18-Jun","170":"19-Jun","171":"20-Jun","172":"21-Jun","173":"22-Jun","174":"23-Jun","175":"24-Jun","176":"25-Jun","177":"26-Jun","178":"27-Jun","179":"28-Jun","180":"29-Jun","181":"30-Jun","182":"01-Jul","183":"02-Jul","184":"03-Jul","185":"04-Jul","186":"05-Jul","187":"06-Jul","188":"07-Jul","189":"08-Jul","190":"09-Jul","191":"10-Jul","192":"11-Jul","193":"12-Jul","194":"13-Jul","195":"14-Jul","196":"15-Jul","197":"16-Jul","198":"17-Jul","199":"18-Jul","200":"19-Jul","201":"20-Jul","202":"21-Jul","203":"22-Jul","204":"23-Jul","205":"24-Jul","206":"25-Jul","207":"26-Jul","208":"27-Jul","209":"28-Jul","210":"29-Jul","211":"30-Jul","212":"31-Jul","213":"01-Aug","214":"02-Aug","215":"03-Aug","216":"04-Aug","217":"05-Aug","218":"06-Aug","219":"07-Aug","220":"08-Aug","221":"09-Aug","222":"10-Aug","223":"11-Aug","224":"12-Aug","225":"13-Aug","226":"14-Aug","227":"15-Aug","228":"16-Aug","229":"17-Aug","230":"18-Aug","231":"19-Aug","232":"20-Aug","233":"21-Aug","234":"22-Aug","235":"23-Aug","236":"24-Aug","237":"25-Aug","238":"26-Aug","239":"27-Aug","240":"28-Aug","241":"29-Aug","242":"30-Aug","243":"31-Aug","244":"01-Sep","245":"02-Sep","246":"03-Sep","247":"04-Sep","248":"05-Sep","249":"06-Sep","250":"07-Sep","251":"08-Sep","252":"09-Sep","253":"10-Sep","254":"11-Sep","255":"12-Sep","256":"13-Sep","257":"14-Sep","258":"15-Sep","259":"16-Sep","260":"17-Sep","261":"18-Sep","262":"19-Sep","263":"20-Sep","264":"21-Sep","265":"22-Sep","266":"23-Sep","267":"24-Sep","268":"25-Sep","269":"26-Sep","270":"27-Sep","271":"28-Sep","272":"29-Sep","273":"30-Sep","274":"01-Oct","275":"02-Oct","276":"03-Oct","277":"04-Oct","278":"05-Oct","279":"06-Oct","280":"07-Oct","281":"08-Oct","282":"09-Oct","283":"10-Oct","284":"11-Oct","285":"12-Oct","286":"13-Oct","287":"14-Oct","288":"15-Oct","289":"16-Oct","290":"17-Oct","291":"18-Oct","292":"19-Oct","293":"20-Oct","294":"21-Oct","295":"22-Oct","296":"23-Oct","297":"24-Oct","298":"25-Oct","299":"26-Oct","300":"27-Oct","301":"28-Oct","302":"29-Oct","303":"30-Oct","304":"31-Oct","305":"01-Nov","306":"02-Nov","307":"03-Nov","308":"04-Nov","309":"05-Nov","310":"06-Nov","311":"07-Nov","312":"08-Nov","313":"09-Nov","314":"10-Nov","315":"11-Nov","316":"12-Nov","317":"13-Nov","318":"14-Nov","319":"15-Nov","320":"16-Nov","321":"17-Nov","322":"18-Nov","323":"19-Nov","324":"20-Nov","325":"21-Nov","326":"22-Nov","327":"23-Nov","328":"24-Nov","329":"25-Nov","330":"26-Nov","331":"27-Nov","332":"28-Nov","333":"29-Nov","334":"30-Nov","335":"01-Dec","336":"02-Dec","337":"03-Dec","338":"04-Dec","339":"05-Dec","340":"06-Dec","341":"07-Dec","342":"08-Dec","343":"09-Dec","344":"10-Dec","345":"11-Dec","346":"12-Dec","347":"13-Dec","348":"14-Dec","349":"15-Dec","350":"16-Dec","351":"17-Dec","352":"18-Dec","353":"19-Dec","354":"20-Dec","355":"21-Dec","356":"22-Dec","357":"23-Dec","358":"24-Dec","359":"25-Dec","360":"26-Dec","361":"27-Dec","362":"28-Dec","363":"29-Dec","364":"30-Dec","365":"31-Dec"},"RAINFALL":{"0":0.61,"1":0.25,"2":0.18,"3":0.3,"4":0.19,"5":0.05,"6":0.55,"7":0.36,"8":0.48,"9":0.17,"10":0.34,"11":0.32,"12":0.53,"13":0.16,"14":0.1,"15":0.06,"16":0.04,"17":0.29,"18":0.12,"19":0.09,"20":0.02,"21":0.02,"22":0.02,"23":0.01,"24":0.03,"25":0.07,"26":0.05,"27":0.24,"28":0.06,"29":0.03,"30":0.1,"31":0.02,"32":0.05,"33":0.0,"34":0.02,"35":0.01,"36":0.26,"37":0.21,"38":0.06,"39":0.05,"40":0.31,"41":0.01,"42":0.13,"43":0.06,"44":0.19,"45":0.47,"46":0.14,"47":0.17,"48":0.06,"49":0.07,"50":0.33,"51":0.11,"52":0.19,"53":0.3,"54":0.36,"55":0.19,"56":0.12,"57":0.14,"58":0.04,"59":0.0,"60":0.03,"61":0.08,"62":0.17,"63":0.22,"64":0.52,"65":0.65,"66":0.34,"67":0.83,"68":0.82,"69":0.43,"70":0.34,"71":0.57,"72":0.46,"73":0.58,"74":0.65,"75":0.64,"76":0.38,"77":0.49,"78":0.69,"79":1.08,"80":0.89,"81":1.24,"82":1.1,"83":1.04,"84":0.85,"85":0.78,"86":0.64,"87":0.89,"88":0.81,"89":0.58,"90":0.82,"91":1.75,"92":1.17,"93":1.44,"94":1.54,"95":1.31,"96":2.11,"97":1.59,"98":1.49,"99":2.41,"100":2.6,"101":3.47,"102":3.22,"103":3.52,"104":3.44,"105":2.93,"106":2.51,"107":2.25,"108":3.2,"109":2.68,"110":3.55,"111":3.55,"112":3.02,"113":4.02,"114":4.43,"115":2.97,"116":2.08,"117":3.49,"118":2.59,"119":3.32,"120":3.93,"121":4.12,"122":4.48,"123":4.81,"124":4.52,"125":4.53,"126":4.38,"127":4.74,"128":3.97,"129":5.25,"130":3.91,"131":4.34,"132":6.84,"133":4.7,"134":4.76,"135":7.14,"136":8.07,"137":6.02,"138":7.69,"139":9.65,"140":9.89,"141":8.08,"142":6.4,"143":6.0,"144":7.75,"145":8.81,"146":9.59,"147":8.06,"148":11.18,"149":13.77,"150":16.17,"151":10.87,"152":14.73,"153":14.96,"154":16.98,"155":16.89,"156":22.25,"157":28.48,"158":25.14,"159":27.12,"160":23.59,"161":25.02,"162":27.14,"163":28.73,"164":31.99,"165":37.97,"166":37.06,"167":34.74,"168":33.51,"169":36.16,"170":35.64,"171":38.68,"172":37.34,"173":37.18,"174":38.71,"175":40.99,"176":36.01,"177":40.97,"178":41.15,"179":42.27,"180":46.65,"181":47.32,"182":49.86,"183":47.79,"184":45.81,"185":45.14,"186":44.11,"187":42.96,"188":41.89,"189":41.76,"190":40.34,"191":42.44,"192":44.58,"193":43.92,"194":40.36,"195":41.8,"196":41.72,"197":40.24,"198":47.35,"199":44.25,"200":44.92,"201":44.81,"202":41.33,"203":43.56,"204":43.48,"205":42.89,"206":42.12,"207":43.94,"208":39.01,"209":39.01,"210":34.75,"211":34.0,"212":36.46,"213":38.9,"214":39.64,"215":35.59,"216":37.89,"217":35.67,"218":36.37,"219":34.37,"220":34.34,"221":32.76,"222":32.73,"223":32.12,"224":33.32,"225":30.34,"226":28.95,"227":30.96,"228":29.92,"229":32.44,"230":28.31,"231":28.51,"232":25.34,"233":24.54,"234":26.92,"235":24.31,"236":23.18,"237":21.67,"238":20.07,"239":18.76,"240":18.23,"241":17.87,"242":16.34,"243":18.01,"244":15.37,"245":15.77,"246":16.29,"247":16.58,"248":16.0,"249":15.09,"250":13.11,"251":14.24,"252":13.84,"253":12.96,"254":12.52,"255":12.22,"256":11.26,"257":9.42,"258":12.47,"259":12.42,"260":10.9,"261":11.66,"262":12.2,"263":14.12,"264":11.18,"265":10.67,"266":9.39,"267":11.36,"268":9.48,"269":12.84,"270":10.05,"271":11.88,"272":12.68,"273":12.13,"274":11.94,"275":14.14,"276":11.8,"277":10.36,"278":10.99,"279":11.89,"280":9.55,"281":9.64,"282":12.43,"283":10.37,"284":9.5,"285":12.46,"286":12.13,"287":11.45,"288":9.1,"289":8.14,"290":9.23,"291":7.44,"292":7.5,"293":10.41,"294":8.07,"295":9.66,"296":9.3,"297":8.51,"298":7.12,"299":7.96,"300":8.08,"301":7.08,"302":8.15,"303":6.77,"304":5.11,"305":7.03,"306":6.8,"307":5.49,"308":4.76,"309":5.17,"310":5.7,"311":7.27,"312":5.74,"313":4.12,"314":3.18,"315":3.14,"316":3.04,"317":2.39,"318":2.73,"319":3.62,"320":3.15,"321":3.53,"322":2.85,"323":1.99,"324":3.14,"325":2.77,"326":3.12,"327":3.87,"328":3.42,"329":2.63,"330":1.01,"331":0.79,"332":0.95,"333":1.23,"334":0.61,"335":1.4,"336":1.91,"337":0.62,"338":0.76,"339":0.47,"340":0.73,"341":0.84,"342":0.58,"343":1.86,"344":1.43,"345":0.76,"346":0.72,"347":1.75,"348":1.5,"349":0.84,"350":0.98,"351":0.69,"352":0.22,"353":0.19,"354":0.06,"355":0.06,"356":0.35,"357":0.16,"358":0.32,"359":0.76,"360":0.55,"361":0.91,"362":0.68,"363":0.55,"364":0.52,"365":0.17}}